{"Edition":"Unlimited Edition","Cards":[{"Name":"Air Elemental","MultiverseId":691},{"Name":"Ancestral Recall","MultiverseId":692},{"Name":"Animate Artifact","MultiverseId":693},{"Name":"Animate Dead","MultiverseId":645},{"Name":"Animate Wall","MultiverseId":829},{"Name":"Ankh of Mishra","MultiverseId":598},{"Name":"Armageddon","MultiverseId":830},{"Name":"Aspect of Wolf","MultiverseId":737},{"Name":"Bad Moon","MultiverseId":646},{"Name":"Badlands","MultiverseId":878},{"Name":"Balance","MultiverseId":831},{"Name":"Basalt Monolith","MultiverseId":599},{"Name":"Bayou","MultiverseId":879},{"Name":"Benalish Hero","MultiverseId":832},{"Name":"Berserk","MultiverseId":738},{"Name":"Birds of Paradise","MultiverseId":739},{"Name":"Black Knight","MultiverseId":647},{"Name":"Black Lotus","MultiverseId":600},{"Name":"Black Vise","MultiverseId":601},{"Name":"Black Ward","MultiverseId":833},{"Name":"Blaze of Glory","MultiverseId":834},{"Name":"Blessing","MultiverseId":835},{"Name":"Blue Elemental Blast","MultiverseId":694},{"Name":"Blue Ward","MultiverseId":836},{"Name":"Bog Wraith","MultiverseId":648},{"Name":"Braingeyser","MultiverseId":695},{"Name":"Burrowing","MultiverseId":783},{"Name":"Camouflage","MultiverseId":740},{"Name":"Castle","MultiverseId":837},{"Name":"Celestial Prism","MultiverseId":602},{"Name":"Channel","MultiverseId":741},{"Name":"Chaos Orb","MultiverseId":603},{"Name":"Chaoslace","MultiverseId":784},{"Name":"Circle of Protection: Black","MultiverseId":838},{"Name":"Circle of Protection: Blue","MultiverseId":839},{"Name":"Circle of Protection: Green","MultiverseId":840},{"Name":"Circle of Protection: Red","MultiverseId":841},{"Name":"Circle of Protection: White","MultiverseId":842},{"Name":"Clockwork Beast","MultiverseId":604},{"Name":"Clone","MultiverseId":696},{"Name":"Cockatrice","MultiverseId":742},{"Name":"Consecrate Land","MultiverseId":843},{"Name":"Conservator","MultiverseId":605},{"Name":"Contract from Below","MultiverseId":649},{"Name":"Control Magic","MultiverseId":697},{"Name":"Conversion","MultiverseId":844},{"Name":"Copper Tablet","MultiverseId":606},{"Name":"Copy Artifact","MultiverseId":698},{"Name":"Counterspell","MultiverseId":699},{"Name":"Craw Wurm","MultiverseId":743},{"Name":"Creature Bond","MultiverseId":700},{"Name":"Crusade","MultiverseId":845},{"Name":"Crystal Rod","MultiverseId":607},{"Name":"Cursed Land","MultiverseId":650},{"Name":"Cyclopean Tomb","MultiverseId":608},{"Name":"Dark Ritual","MultiverseId":651},{"Name":"Darkpact","MultiverseId":652},{"Name":"Death Ward","MultiverseId":846},{"Name":"Deathgrip","MultiverseId":653},{"Name":"Deathlace","MultiverseId":654},{"Name":"Demonic Attorney","MultiverseId":655},{"Name":"Demonic Hordes","MultiverseId":656},{"Name":"Demonic Tutor","MultiverseId":657},{"Name":"Dingus Egg","MultiverseId":609},{"Name":"Disenchant","MultiverseId":847},{"Name":"Disintegrate","MultiverseId":785},{"Name":"Disrupting Scepter","MultiverseId":610},{"Name":"Dragon Whelp","MultiverseId":786},{"Name":"Drain Life","MultiverseId":658},{"Name":"Drain Power","MultiverseId":701},{"Name":"Drudge Skeletons","MultiverseId":659},{"Name":"Dwarven Demolition Team","MultiverseId":787},{"Name":"Dwarven Warriors","MultiverseId":788},{"Name":"Earth Elemental","MultiverseId":789},{"Name":"Earthbind","MultiverseId":790},{"Name":"Earthquake","MultiverseId":791},{"Name":"Elvish Archers","MultiverseId":744},{"Name":"Evil Presence","MultiverseId":660},{"Name":"False Orders","MultiverseId":792},{"Name":"Farmstead","MultiverseId":848},{"Name":"Fastbond","MultiverseId":745},{"Name":"Fear","MultiverseId":661},{"Name":"Feedback","MultiverseId":702},{"Name":"Fire Elemental","MultiverseId":793},{"Name":"Fireball","MultiverseId":794},{"Name":"Firebreathing","MultiverseId":795},{"Name":"Flashfires","MultiverseId":796},{"Name":"Flight","MultiverseId":703},{"Name":"Fog","MultiverseId":746},{"Name":"Force of Nature","MultiverseId":747},{"Name":"Forcefield","MultiverseId":611},{"Name":"Forest","MultiverseId":889},{"Name":"Fork","MultiverseId":797},{"Name":"Frozen Shade","MultiverseId":662},{"Name":"Fungusaur","MultiverseId":748},{"Name":"Gaea's Liege","MultiverseId":749},{"Name":"Gauntlet of Might","MultiverseId":612},{"Name":"Giant Growth","MultiverseId":750},{"Name":"Giant Spider","MultiverseId":751},{"Name":"Glasses of Urza","MultiverseId":613},{"Name":"Gloom","MultiverseId":663},{"Name":"Goblin Balloon Brigade","MultiverseId":798},{"Name":"Goblin King","MultiverseId":799},{"Name":"Granite Gargoyle","MultiverseId":800},{"Name":"Gray Ogre","MultiverseId":801},{"Name":"Green Ward","MultiverseId":849},{"Name":"Grizzly Bears","MultiverseId":752},{"Name":"Guardian Angel","MultiverseId":850},{"Name":"Healing Salve","MultiverseId":851},{"Name":"Helm of Chatzuk","MultiverseId":614},{"Name":"Hill Giant","MultiverseId":802},{"Name":"Holy Armor","MultiverseId":852},{"Name":"Holy Strength","MultiverseId":853},{"Name":"Howl from Beyond","MultiverseId":664},{"Name":"Howling Mine","MultiverseId":615},{"Name":"Hurloon Minotaur","MultiverseId":803},{"Name":"Hurricane","MultiverseId":753},{"Name":"Hypnotic Specter","MultiverseId":665},{"Name":"Ice Storm","MultiverseId":754},{"Name":"Icy Manipulator","MultiverseId":616},{"Name":"Illusionary Mask","MultiverseId":617},{"Name":"Instill Energy","MultiverseId":755},{"Name":"Invisibility","MultiverseId":704},{"Name":"Iron Star","MultiverseId":618},{"Name":"Ironclaw Orcs","MultiverseId":804},{"Name":"Ironroot Treefolk","MultiverseId":756},{"Name":"Island","MultiverseId":896},{"Name":"Island Sanctuary","MultiverseId":854},{"Name":"Ivory Cup","MultiverseId":619},{"Name":"Jade Monolith","MultiverseId":620},{"Name":"Jade Statue","MultiverseId":621},{"Name":"Jayemdae Tome","MultiverseId":622},{"Name":"Juggernaut","MultiverseId":623},{"Name":"Jump","MultiverseId":705},{"Name":"Karma","MultiverseId":855},{"Name":"Keldon Warlord","MultiverseId":805},{"Name":"Kormus Bell","MultiverseId":624},{"Name":"Kudzu","MultiverseId":757},{"Name":"Lance","MultiverseId":856},{"Name":"Ley Druid","MultiverseId":758},{"Name":"Library of Leng","MultiverseId":625},{"Name":"Lich","MultiverseId":666},{"Name":"Lifeforce","MultiverseId":759},{"Name":"Lifelace","MultiverseId":760},{"Name":"Lifetap","MultiverseId":706},{"Name":"Lightning Bolt","MultiverseId":806},{"Name":"Living Artifact","MultiverseId":761},{"Name":"Living Lands","MultiverseId":762},{"Name":"Living Wall","MultiverseId":626},{"Name":"Llanowar Elves","MultiverseId":763},{"Name":"Lord of Atlantis","MultiverseId":707},{"Name":"Lord of the Pit","MultiverseId":667},{"Name":"Lure","MultiverseId":764},{"Name":"Magical Hack","MultiverseId":708},{"Name":"Mahamoti Djinn","MultiverseId":709},{"Name":"Mana Flare","MultiverseId":807},{"Name":"Mana Short","MultiverseId":710},{"Name":"Mana Vault","MultiverseId":627},{"Name":"Manabarbs","MultiverseId":808},{"Name":"Meekstone","MultiverseId":628},{"Name":"Merfolk of the Pearl Trident","MultiverseId":711},{"Name":"Mesa Pegasus","MultiverseId":857},{"Name":"Mind Twist","MultiverseId":668},{"Name":"Mons's Goblin Raiders","MultiverseId":809},{"Name":"Mountain","MultiverseId":891},{"Name":"Mox Emerald","MultiverseId":629},{"Name":"Mox Jet","MultiverseId":630},{"Name":"Mox Pearl","MultiverseId":631},{"Name":"Mox Ruby","MultiverseId":632},{"Name":"Mox Sapphire","MultiverseId":633},{"Name":"Natural Selection","MultiverseId":765},{"Name":"Nether Shadow","MultiverseId":669},{"Name":"Nettling Imp","MultiverseId":670},{"Name":"Nevinyrral's Disk","MultiverseId":634},{"Name":"Nightmare","MultiverseId":671},{"Name":"Northern Paladin","MultiverseId":858},{"Name":"Obsianus Golem","MultiverseId":635},{"Name":"Orcish Artillery","MultiverseId":810},{"Name":"Orcish Oriflamme","MultiverseId":811},{"Name":"Paralyze","MultiverseId":672},{"Name":"Pearled Unicorn","MultiverseId":859},{"Name":"Personal Incarnation","MultiverseId":860},{"Name":"Pestilence","MultiverseId":673},{"Name":"Phantasmal Forces","MultiverseId":712},{"Name":"Phantasmal Terrain","MultiverseId":713},{"Name":"Phantom Monster","MultiverseId":714},{"Name":"Pirate Ship","MultiverseId":715},{"Name":"Plague Rats","MultiverseId":674},{"Name":"Plains","MultiverseId":899},{"Name":"Plateau","MultiverseId":880},{"Name":"Power Leak","MultiverseId":716},{"Name":"Power Sink","MultiverseId":717},{"Name":"Power Surge","MultiverseId":812},{"Name":"Prodigal Sorcerer","MultiverseId":718},{"Name":"Psionic Blast","MultiverseId":719},{"Name":"Psychic Venom","MultiverseId":720},{"Name":"Purelace","MultiverseId":861},{"Name":"Raging River","MultiverseId":813},{"Name":"Raise Dead","MultiverseId":675},{"Name":"Red Elemental Blast","MultiverseId":814},{"Name":"Red Ward","MultiverseId":862},{"Name":"Regeneration","MultiverseId":766},{"Name":"Regrowth","MultiverseId":767},{"Name":"Resurrection","MultiverseId":863},{"Name":"Reverse Damage","MultiverseId":864},{"Name":"Righteousness","MultiverseId":865},{"Name":"Roc of Kher Ridges","MultiverseId":815},{"Name":"Rock Hydra","MultiverseId":816},{"Name":"Rod of Ruin","MultiverseId":636},{"Name":"Royal Assassin","MultiverseId":676},{"Name":"Sacrifice","MultiverseId":677},{"Name":"Samite Healer","MultiverseId":866},{"Name":"Savannah","MultiverseId":881},{"Name":"Savannah Lions","MultiverseId":867},{"Name":"Scathe Zombies","MultiverseId":678},{"Name":"Scavenging Ghoul","MultiverseId":679},{"Name":"Scrubland","MultiverseId":882},{"Name":"Scryb Sprites","MultiverseId":768},{"Name":"Sea Serpent","MultiverseId":721},{"Name":"Sedge Troll","MultiverseId":817},{"Name":"Sengir Vampire","MultiverseId":680},{"Name":"Serra Angel","MultiverseId":868},{"Name":"Shanodin Dryads","MultiverseId":769},{"Name":"Shatter","MultiverseId":818},{"Name":"Shivan Dragon","MultiverseId":819},{"Name":"Simulacrum","MultiverseId":681},{"Name":"Sinkhole","MultiverseId":682},{"Name":"Siren's Call","MultiverseId":722},{"Name":"Sleight of Mind","MultiverseId":723},{"Name":"Smoke","MultiverseId":820},{"Name":"Sol Ring","MultiverseId":637},{"Name":"Soul Net","MultiverseId":638},{"Name":"Spell Blast","MultiverseId":724},{"Name":"Stasis","MultiverseId":725},{"Name":"Steal Artifact","MultiverseId":726},{"Name":"Stone Giant","MultiverseId":821},{"Name":"Stone Rain","MultiverseId":822},{"Name":"Stream of Life","MultiverseId":770},{"Name":"Sunglasses of Urza","MultiverseId":639},{"Name":"Swamp","MultiverseId":876},{"Name":"Swords to Plowshares","MultiverseId":869},{"Name":"Taiga","MultiverseId":883},{"Name":"Terror","MultiverseId":683},{"Name":"The Hive","MultiverseId":640},{"Name":"Thicket Basilisk","MultiverseId":771},{"Name":"Thoughtlace","MultiverseId":727},{"Name":"Throne of Bone","MultiverseId":641},{"Name":"Timber Wolves","MultiverseId":772},{"Name":"Time Vault","MultiverseId":642},{"Name":"Time Walk","MultiverseId":728},{"Name":"Timetwister","MultiverseId":729},{"Name":"Tranquility","MultiverseId":773},{"Name":"Tropical Island","MultiverseId":884},{"Name":"Tsunami","MultiverseId":774},{"Name":"Tundra","MultiverseId":885},{"Name":"Tunnel","MultiverseId":823},{"Name":"Twiddle","MultiverseId":730},{"Name":"Two-Headed Giant of Foriys","MultiverseId":824},{"Name":"Underground Sea","MultiverseId":886},{"Name":"Unholy Strength","MultiverseId":684},{"Name":"Unsummon","MultiverseId":731},{"Name":"Uthden Troll","MultiverseId":825},{"Name":"Verduran Enchantress","MultiverseId":775},{"Name":"Vesuvan Doppelganger","MultiverseId":732},{"Name":"Veteran Bodyguard","MultiverseId":870},{"Name":"Volcanic Eruption","MultiverseId":733},{"Name":"Volcanic Island","MultiverseId":887},{"Name":"Wall of Air","MultiverseId":734},{"Name":"Wall of Bone","MultiverseId":685},{"Name":"Wall of Brambles","MultiverseId":776},{"Name":"Wall of Fire","MultiverseId":826},{"Name":"Wall of Ice","MultiverseId":777},{"Name":"Wall of Stone","MultiverseId":827},{"Name":"Wall of Swords","MultiverseId":871},{"Name":"Wall of Water","MultiverseId":735},{"Name":"Wall of Wood","MultiverseId":778},{"Name":"Wanderlust","MultiverseId":779},{"Name":"War Mammoth","MultiverseId":780},{"Name":"Warp Artifact","MultiverseId":686},{"Name":"Water Elemental","MultiverseId":736},{"Name":"Weakness","MultiverseId":687},{"Name":"Web","MultiverseId":781},{"Name":"Wheel of Fortune","MultiverseId":828},{"Name":"White Knight","MultiverseId":872},{"Name":"White Ward","MultiverseId":873},{"Name":"Wild Growth","MultiverseId":782},{"Name":"Will-o'-the-Wisp","MultiverseId":688},{"Name":"Winter Orb","MultiverseId":643},{"Name":"Wooden Sphere","MultiverseId":644},{"Name":"Word of Command","MultiverseId":689},{"Name":"Wrath of God","MultiverseId":874},{"Name":"Zombie Master","MultiverseId":690}]}